ants_extractor
