Metadata-Version: 2.1
Name: ants-fts
Version: 0.2.2
Summary: This library is used to extract features from data.
Home-page: https://ants.abc
Author: HaoPP
Author-email: haopp@antsomi.com
Project-URL: Source, https://ants.abc/source
Project-URL: Documentation, https://ants.abc/docs
Classifier: Programming Language :: Python :: 3
Classifier: Programming Language :: Python :: 3.7
Classifier: License :: OSI Approved :: MIT License
Classifier: Operating System :: OS Independent
Classifier: Intended Audience :: Developers
Classifier: Natural Language :: English
Requires-Python: >=3.7
